templaterepo/__init__.py
testrepo8/__init__.py
testrepo8-0.0.0.dist-info/LICENSE
testrepo8-0.0.0.dist-info/METADATA
testrepo8-0.0.0.dist-info/WHEEL
testrepo8-0.0.0.dist-info/top_level.txt
testrepo8-0.0.0.dist-info/RECORD
