Metadata-Version: 2.1
Name: testrepo8
Version: 0.0.0
Summary: ryhryh
Author: Armin Ariamajd
Maintainer: Armin Ariamajd
License: GNU AFFERO GENERAL PUBLIC LICENSE
Project-URL: Homepage, https://aariam.github.io/TestRepo8
Project-URL: Download, https://github.com/AAriam/TestRepo8/releases
Project-URL: News, https://aariam.github.io/TestRepo8/news
Project-URL: Documentation, https://aariam.github.io/TestRepo8
Project-URL: Bug Tracker, https://github.com/AAriam/TestRepo8/issues
Project-URL: Sponsor, https://aariam.github.io/TestRepo8/contribute/collaborate/maintain/sponsor
Project-URL: Source, https://github.com/AAriam/TestRepo8
Keywords: python,github,packaging,template,dynamic repository,repository template,documentation,testing,deployment,maintenance,automation,development,infrastructure,streamline
Classifier: Typing :: Typed
Classifier: Natural Language :: English
Classifier: License :: OSI Approved :: GNU Affero General Public License v3 or later (AGPLv3+)
Classifier: Development Status :: 1 - Planning
Classifier: Programming Language :: Python :: 3 :: Only
Classifier: Programming Language :: Python :: 3.9
Classifier: Programming Language :: Python :: 3.10
Classifier: Programming Language :: Python :: 3.11
Classifier: Operating System :: POSIX :: Linux
Classifier: Operating System :: MacOS
Classifier: Operating System :: Microsoft :: Windows
Requires-Python: >=3.9
License-File: LICENSE
Requires-Dist: numpy >=1.21.2
